[
  {
    "model": "products.productcategory",
    "pk": 1,
    "fields": {
      "name": "Новинки",
      "description": "Новые поступления"
    }
  },
  {
    "model": "products.productcategory",
    "pk": 2,
    "fields": {
      "name": "Одежда",
      "description": "Вещи на любой сезон"
    }
  },
  {
    "model": "products.productcategory",
    "pk": 3,
    "fields": {
      "name": "Обувь",
      "description": "Обувь на любой сезон"
    }
  },
  {
    "model": "products.productcategory",
    "pk": 4,
    "fields": {
      "name": "Аксессуары",
      "description": "Дополни свой образ аксессуарами"
    }
  },
  {
    "model": "products.productcategory",
    "pk": 5,
    "fields": {
      "name": "Подарки",
      "description": "Сделай приятное своим близким"
    }
  }
]
